mathct/__init__.py
mathct/main.py
mathct-1.0.0.dist-info/LICENSE
mathct-1.0.0.dist-info/METADATA
mathct-1.0.0.dist-info/WHEEL
mathct-1.0.0.dist-info/top_level.txt
mathct-1.0.0.dist-info/RECORD
